LICENSE
MANIFEST.in
README.md
setup.py
src/wheezy/__init__.py
src/wheezy.html.egg-info/PKG-INFO
src/wheezy.html.egg-info/SOURCES.txt
src/wheezy.html.egg-info/dependency_links.txt
src/wheezy.html.egg-info/namespace_packages.txt
src/wheezy.html.egg-info/not-zip-safe
src/wheezy.html.egg-info/requires.txt
src/wheezy.html.egg-info/top_level.txt
src/wheezy/html/__init__.py
src/wheezy/html/boost.c
src/wheezy/html/utils.py
src/wheezy/html/ext/__init__.py
src/wheezy/html/ext/jinja2.py
src/wheezy/html/ext/lexer.py
src/wheezy/html/ext/mako.py
src/wheezy/html/ext/parser.py
src/wheezy/html/ext/template.py
src/wheezy/html/ext/tenjin.py