Metadata-Version: 2.1
Name: wheezy.html
Version: 3.0.0
Summary: A lightweight html rendering library
Home-page: https://github.com/akornatskyy/wheezy.html
Author: Andriy Kornatskyy
Author-email: andriy.kornatskyy@live.com
License: MIT
Keywords: html widget markup mako jinja2 tenjin wheezy.template preprocessor
Platform: any
Classifier: Environment :: Web Environment
Classifier: Intended Audience :: Developers
Classifier: License :: OSI Approved :: MIT License
Classifier: Natural Language :: English
Classifier: Operating System :: OS Independent
Classifier: Programming Language :: Python
Classifier: Programming Language :: Python :: 3.6
Classifier: Programming Language :: Python :: 3.7
Classifier: Programming Language :: Python :: 3.8
Classifier: Programming Language :: Python :: 3.9
Classifier: Programming Language :: Python :: Implementation :: CPython
Classifier: Programming Language :: Python :: Implementation :: PyPy
Classifier: Topic :: Internet :: WWW/HTTP
Classifier: Topic :: Internet :: WWW/HTTP :: Dynamic Content
Classifier: Topic :: Software Development :: Libraries :: Python Modules
Classifier: Topic :: Software Development :: Widget Sets
Classifier: Topic :: Text Processing :: Markup :: HTML
Requires-Python: >=3.6
Provides-Extra: mako
Provides-Extra: tenjin
Provides-Extra: jinja2
Provides-Extra: wheezy.template
